pdopt/__init__.py
pdopt/data.py
pdopt/exploration.py
pdopt/optimisation.py
pdopt/tools.py
pdopt/visualisation.py
pdopt-0.5.1.dist-info/LICENSE
pdopt-0.5.1.dist-info/METADATA
pdopt-0.5.1.dist-info/WHEEL
pdopt-0.5.1.dist-info/top_level.txt
pdopt-0.5.1.dist-info/zip-safe
pdopt-0.5.1.dist-info/RECORD
