Metadata-Version: 2.1
Name: pdopt
Version: 0.5.1
Summary: Package for Probabilistic Design Space Exploration using Set-Based Design
Home-page: https://github.com/spinjet/pdopt-code
Author: Andrea Spinelli
Author-email: andrea.spinelli@cranfield.ac.uk
License: MIT License
Keywords: set-based design,design space exploration,optimization,engineering design
Classifier: License :: OSI Approved :: MIT License
Classifier: Programming Language :: Python :: 3
License-File: LICENSE
Requires-Dist: numpy
Requires-Dist: scipy
Requires-Dist: matplotlib
Requires-Dist: pandas
Requires-Dist: scikit-learn
Requires-Dist: pymoo >=0.6.0
Requires-Dist: joblib
Requires-Dist: tqdm
Provides-Extra: viz
Requires-Dist: plotly ; extra == 'viz'
Requires-Dist: dash ; extra == 'viz'
